Workbook

Sheet Configuración
A1: ⚙ CONFIGURACIÓN — Tasas y costos logísticos
A3: TASAS DE CAMBIO
A4: INR por 1 USD | B4: 95 | C4: ₹/USD | D4: Rupia india — actualizar según XE.com
A5: Bs.D por 1 USD | B5: 715 | C5: Bs.D/USD | D5: BCV o paralelo
A7: SHOPPRE — ENVÍO INDIA→USA (DUTY FREE)
A8: ¿Miembro Shoppre? | B8: FALSE | C8: Sí / No | D8: Marca la casilla si eres miembro Shoppre (tarifa con descuento). Sin marcar = tarifa normal.
A9: Peso de referencia Catálogo (kg) | B9: 15 | C9: kg | D9: Peso típico que usas para FIJAR los precios del catálogo. No cambia aunque calcules envíos reales.
A10: $/kg referencia Catálogo (auto) | B10: =IF($B$9="","",IFERROR(ROUND((IF($B$8,INDEX('Tarifas Shoppre'!$E$4:$E$219,MATCH(MIN(22,MAX(0.5,ROUND(CEILING($B$9,0.1),1))),'Tarifas Shoppre'!$A$4:$A$219,1)),INDEX('Tarifas Shoppre'!$D$4:$D$219,MATCH(MIN(22,MAX(0.5,ROUND(CEILING($B$9,0.1),1))),'Tarifas Shoppre'!$A$4:$A$219,1))))/$B$9,2),"")) -> 16.62 | C10: USD/kg | D10: Reparte el envío por ítem en Catálogo, Calculadora y Próximo Pedido.
A11: Peso del envío actual (kg) | B11: 15 | C11: kg | D11: Kilos de UN envío puntual que quieras cotizar. Independiente del catálogo (0.5 a 22 kg).
A12: Costo Duty Free del envío ($) | B12: =IFERROR(ROUND(IF($B$8,INDEX('Tarifas Shoppre'!$E$4:$E$219,MATCH(MIN(22,MAX(0.5,ROUND(CEILING($B$11,0.1),1))),'Tarifas Shoppre'!$A$4:$A$219,1)),INDEX('Tarifas Shoppre'!$D$4:$D$219,MATCH(MIN(22,MAX(0.5,ROUND(CEILING($B$11,0.1),1))),'Tarifas Shoppre'!$A$4:$A$219,1))),2),"") -> 249.29 | C12: USD | D12: Precio real de la tabla a ese peso. Para varios paquetes usa el Simulador.
A14: OTROS COSTOS LOGÍSTICOS
A15: Miami → Caracas (Marítimo) | B15: 45 | C15: USD/ft³ | D15: Marítimo por pie cúbico. Actualizar con tarifa real del casillero.
A16: Seguro Shoppre (% sobre declarado) | B16: 0.03 | C16: % | D16: 3% del valor declarado. Se aplica una vez en Próximo Pedido.
A17: Processing fee Shoppre (fijo) | B17: 500 | C17: INR | D17: ₹500 fijos por envío consolidado.
A18: Seguro Marítimo Miami→CCS (%) | B18: 0 | C18: % | D18: % del valor. Dejar en 0 si no aplica.
A20: SENIAT — ADUANA VENEZUELA
A21: Umbral libre de impuesto (USD) | B21: 0 | C21: USD | D21: Valor declarado bajo el cual no paga SENIAT. 0 si no aplica.
A22: Tasa SENIAT sobre umbral (%) | B22: 0 | C22: % | D22: % sobre el declarado cuando supera el umbral. 0 si no aplica.
A24: LEYENDA DE COLORES
A25: ▉ | B25: Azul → Dato de entrada (editar libremente)
A26: ▉ | B26: Negro → Fórmula calculada (no editar)
A27: ▉ | B27: Amarillo → Celdas clave: membresía, peso de referencia y peso de envío

Sheet Tarifas Shoppre
A1: 🚚 TARIFAS SHOPPRE — ShipGlobal Duty Free (India → USA)
A2: Tarifa Duty Free real (arancel USA incluido por Shoppre). Hasta 22 kg. Costo por kilo para member (con descuento) y normal (basic). El check de membresía en Configuración decide cuál usan los cálculos. Shoppre cobra por slab de 0.1 kg redondeando hacia arriba.
A3: Peso (kg) | B3: INR basic | C3: INR member | D3: USD basic ($) | E3: USD member ($) | F3: $/kg basic | G3: $/kg member
A4: 0.5 | B4: 1968 | C4: 1870 | D4: =ROUND(B4/Configuración!$B$4,2) -> 20.72 | E4: =ROUND(C4/Configuración!$B$4,2) -> 19.68 | F4: =IF(A4=0,"",ROUND(D4/A4,2)) -> 41.44 | G4: =IF(A4=0,"",ROUND(E4/A4,2)) -> 39.36
A5: 0.6 | B5: 2139 | C5: 2032 | D5: =ROUND(B5/Configuración!$B$4,2) -> 22.52 | E5: =ROUND(C5/Configuración!$B$4,2) -> 21.39 | F5: =IF(A5=0,"",ROUND(D5/A5,2)) -> 37.53 | G5: =IF(A5=0,"",ROUND(E5/A5,2)) -> 35.65
A6: 0.7 | B6: 2928 | C6: 2782 | D6: =ROUND(B6/Configuración!$B$4,2) -> 30.82 | E6: =ROUND(C6/Configuración!$B$4,2) -> 29.28 | F6: =IF(A6=0,"",ROUND(D6/A6,2)) -> 44.03 | G6: =IF(A6=0,"",ROUND(E6/A6,2)) -> 41.83
A7: 0.8 | B7: 2478 | C7: 2354 | D7: =ROUND(B7/Configuración!$B$4,2) -> 26.08 | E7: =ROUND(C7/Configuración!$B$4,2) -> 24.78 | F7: =IF(A7=0,"",ROUND(D7/A7,2)) -> 32.6 | G7: =IF(A7=0,"",ROUND(E7/A7,2)) -> 30.98
A8: 0.9 | B8: 2647 | C8: 2515 | D8: =ROUND(B8/Configuración!$B$4,2) -> 27.86 | E8: =ROUND(C8/Configuración!$B$4,2) -> 26.47 | F8: =IF(A8=0,"",ROUND(D8/A8,2)) -> 30.96 | G8: =IF(A8=0,"",ROUND(E8/A8,2)) -> 29.41
A9: 1 | B9: 2928 | C9: 2782 | D9: =ROUND(B9/Configuración!$B$4,2) -> 30.82 | E9: =ROUND(C9/Configuración!$B$4,2) -> 29.28 | F9: =IF(A9=0,"",ROUND(D9/A9,2)) -> 30.82 | G9: =IF(A9=0,"",ROUND(E9/A9,2)) -> 29.28
A10: 1.1 | B10: 2937 | C10: 2790 | D10: =ROUND(B10/Configuración!$B$4,2) -> 30.92 | E10: =ROUND(C10/Configuración!$B$4,2) -> 29.37 | F10: =IF(A10=0,"",ROUND(D10/A10,2)) -> 28.11 | G10: =IF(A10=0,"",ROUND(E10/A10,2)) -> 26.7
A11: 1.2 | B11: 3102 | C11: 2947 | D11: =ROUND(B11/Configuración!$B$4,2) -> 32.65 | E11: =ROUND(C11/Configuración!$B$4,2) -> 31.02 | F11: =IF(A11=0,"",ROUND(D11/A11,2)) -> 27.21 | G11: =IF(A11=0,"",ROUND(E11/A11,2)) -> 25.85
A12: 1.3 | B12: 3265 | C12: 3101 | D12: =ROUND(B12/Configuración!$B$4,2) -> 34.37 | E12: =ROUND(C12/Configuración!$B$4,2) -> 32.64 | F12: =IF(A12=0,"",ROUND(D12/A12,2)) -> 26.44 | G12: =IF(A12=0,"",ROUND(E12/A12,2)) -> 25.11
A13: 1.4 | B13: 3520 | C13: 3344 | D13: =ROUND(B13/Configuración!$B$4,2) -> 37.05 | E13: =ROUND(C13/Configuración!$B$4,2) -> 35.2 | F13: =IF(A13=0,"",ROUND(D13/A13,2)) -> 26.46 | G13: =IF(A13=0,"",ROUND(E13/A13,2)) -> 25.14
A14: 1.5 | B14: 3684 | C14: 3500 | D14: =ROUND(B14/Configuración!$B$4,2) -> 38.78 | E14: =ROUND(C14/Configuración!$B$4,2) -> 36.84 | F14: =IF(A14=0,"",ROUND(D14/A14,2)) -> 25.85 | G14: =IF(A14=0,"",ROUND(E14/A14,2)) -> 24.56
A15: 1.6 | B15: 3848 | C15: 3655 | D15: =ROUND(B15/Configuración!$B$4,2) -> 40.51 | E15: =ROUND(C15/Configuración!$B$4,2) -> 38.47 | F15: =IF(A15=0,"",ROUND(D15/A15,2)) -> 25.32 | G15: =IF(A15=0,"",ROUND(E15/A15,2)) -> 24.04
... A219: 22 | B219: 32912 | C219: 31266 | D219: =ROUND(B219/Configuración!$B$4,2) -> 346.44 | E219: =ROUND(C219/Configuración!$B$4,2) -> 329.12 | F219: =IF(A219=0,"",ROUND(D219/A219,2)) -> 15.75 | G219: =IF(A219=0,"",ROUND(E219/A219,2)) -> 14.96

Sheet Catálogo
A1: 📦 CATÁLOGO DE PRODUCTOS — Pulsar N250
A2: Registra cada pieza con peso y medidas. Desde aquí se añade directo a la Calculadora.
A4: Producto | B4: Código | C4: Motos compatibles | D4: Categoría | E4: Peso real (gramos) | F4: L (cm) | G4: A (cm) | H4: H (cm) | I4: Vol. L×A×H (cm³) | J4: Peso Volumetrico | K4: Precio India (INR ₹) | L4: Costo ($) | M4: Envío India→USA ($) | N4: Envío USA→CCS ($) | O4: Seguro Shoppre ($) | P4: Seguro Miami→CCS ($) | Q4: Costo total landed ($) | R4: Notas / variantes | S4: Margen (%) | T4: Precio venta ($) | U4: Ganancia ($)
A5: Kit cadena (cadena + 2 catarinas) | B5: 36JR0033 | C5: Pulsar N250(a) | D5: Transmisión | E5: 3052 | F5: 25 | G5: 20 | H5: 8 | I5: =IF(OR(F5="",G5="",H5=""),"",F5*G5*H5) -> 4000 | J5: =IF(I5="","",I5/5000) -> 0.8 | K5: 2295 | L5: =IF(K5="","",ROUND(K5/Configuración!$B$4,2)) -> 24.16 | M5: =IF(E5="","",ROUND(MAX(E5/1000,IF(I5="",0,I5/5000))*Configuración!$B$10,2)) -> 50.72 | N5: =IF(I5="","",ROUND(I5/28316.85*Configuración!$B$15,2)) -> 6.36 | O5: =IF(L5="","",ROUND(L5*Configuración!$B$16,2)) -> 0.72 | P5: =IF(L5="","",ROUND(L5*Configuración!$B$18,2)) -> 0 | Q5: =IF(L5="","",ROUND(L5+IF(M5="",0,M5)+IF(N5="",0,N5)+IF(O5="",0,O5)+IF(P5="",0,P5),2)) -> 81.96 | R5: Kit Chain Sprocket — chain 428 + corona trasera + piñón delantero. Peso medido real. | S5: 0.4 | T5: =IF(Q5="","",ROUND(Q5/(1-S5),0)) -> 137 | U5: =IF(T5="","",ROUND(T5-Q5,2)) -> 55.04
A6: Bujía NGK (x1) | B6: JL351218 | C6: Pulsar N250 | D6: Mantenimiento | E6: 50 | F6: 6 | G6: 4 | H6: 4 | I6: =IF(OR(F6="",G6="",H6=""),"",F6*G6*H6) -> 96 | J6: =IF(I6="","",I6/5000) -> 0.0192 | K6: 155 | L6: =IF(K6="","",ROUND(K6/Configuración!$B$4,2)) -> 1.63 | M6: =IF(E6="","",ROUND(MAX(E6/1000,IF(I6="",0,I6/5000))*Configuración!$B$10,2)) -> 0.83 | N6: =IF(I6="","",ROUND(I6/28316.85*Configuración!$B$15,2)) -> 0.15 | O6: =IF(L6="","",ROUND(L6*Configuración!$B$16,2)) -> 0.05 | P6: =IF(L6="","",ROUND(L6*Configuración!$B$18,2)) -> 0 | Q6: =IF(L6="","",ROUND(L6+IF(M6="",0,M6)+IF(N6="",0,N6)+IF(O6="",0,O6)+IF(P6="",0,P6),2)) -> 2.66 | R6: Plug Spark — también ref JL351217. Incluir en regalos/kits, no vender sola. | S6: 0.4 | T6: =IF(Q6="","",ROUND(Q6/(1-S6),0)) -> 4 | U6: =IF(T6="","",ROUND(T6-Q6,2)) -> 1.34
A7: Bujía Bosch RG6HCC (x1) | B7: DK111028 | C7: Pulsar N250 | D7: Mantenimiento | E7: 40 | F7: 6 | G7: 4 | H7: 4 | I7: =IF(OR(F7="",G7="",H7=""),"",F7*G7*H7) -> 96 | J7: =IF(I7="","",I7/5000) -> 0.0192 | K7: 120 | L7: =IF(K7="","",ROUND(K7/Configuración!$B$4,2)) -> 1.26 | M7: =IF(E7="","",ROUND(MAX(E7/1000,IF(I7="",0,I7/5000))*Configuración!$B$10,2)) -> 0.66 | N7: =IF(I7="","",ROUND(I7/28316.85*Configuración!$B$15,2)) -> 0.15 | O7: =IF(L7="","",ROUND(L7*Configuración!$B$16,2)) -> 0.04 | P7: =IF(L7="","",ROUND(L7*Configuración!$B$18,2)) -> 0 | Q7: =IF(L7="","",ROUND(L7+IF(M7="",0,M7)+IF(N7="",0,N7)+IF(O7="",0,O7)+IF(P7="",0,P7),2)) -> 2.11 | R7: Spark Plug RG6HCC — también ref DT351206. | S7: 0.4 | T7: =IF(Q7="","",ROUND(Q7/(1-S7),0)) -> 4 | U7: =IF(T7="","",ROUND(T7-Q7,2)) -> 1.89
A8: Filtro aire (kit elemento + sello) | B8: 36JR0043 | C8: Pulsar N250/N160 | D8: Mantenimiento | E8: 180 | F8: 15 | G8: 12 | H8: 5 | I8: =IF(OR(F8="",G8="",H8=""),"",F8*G8*H8) -> 900 | J8: =IF(I8="","",I8/5000) -> 0.18 | K8: 251 | L8: =IF(K8="","",ROUND(K8/Configuración!$B$4,2)) -> 2.64 | M8: =IF(E8="","",ROUND(MAX(E8/1000,IF(I8="",0,I8/5000))*Configuración!$B$10,2)) -> 2.99 | N8: =IF(I8="","",ROUND(I8/28316.85*Configuración!$B$15,2)) -> 1.43 | O8: =IF(L8="","",ROUND(L8*Configuración!$B$16,2)) -> 0.08 | P8: =IF(L8="","",ROUND(L8*Configuración!$B$18,2)) -> 0 | Q8: =IF(L8="","",ROUND(L8+IF(M8="",0,M8)+IF(N8="",0,N8)+IF(O8="",0,O8)+IF(P8="",0,P8),2)) -> 7.14 | R8: Kit Air Filter Element + Seal — completo. | S8: 0.4 | T8: =IF(Q8="","",ROUND(Q8/(1-S8),0)) -> 12 | U8: =IF(T8="","",ROUND(T8-Q8,2)) -> 4.86
A9: Filtro aceite (x1) | B9: JG571014 | C9: Pulsar N250/N160/NS200/D400 | D9: Mantenimiento | E9: 85 | F9: 8 | G9: 7 | H9: 6 | I9: =IF(OR(F9="",G9="",H9=""),"",F9*G9*H9) -> 336 | J9: =IF(I9="","",I9/5000) -> 0.0672 | K9: 82 | L9: =IF(K9="","",ROUND(K9/Configuración!$B$4,2)) -> 0.86 | M9: =IF(E9="","",ROUND(MAX(E9/1000,IF(I9="",0,I9/5000))*Configuración!$B$10,2)) -> 1.41 | N9: =IF(I9="","",ROUND(I9/28316.85*Configuración!$B$15,2)) -> 0.53 | O9: =IF(L9="","",ROUND(L9*Configuración!$B$16,2)) -> 0.03 | P9: =IF(L9="","",ROUND(L9*Configuración!$B$18,2)) -> 0 | Q9: =IF(L9="","",ROUND(L9+IF(M9="",0,M9)+IF(N9="",0,N9)+IF(O9="",0,O9)+IF(P9="",0,P9),2)) -> 2.83 | R9: Oil Filter + O-Ring LJA00022. Usar como regalo en pedidos grandes.El O-ring solo sirve para N250 y N160 | S9: 0.4 | T9: =IF(Q9="","",ROUND(Q9/(1-S9),0)) -> 5 | U9: =IF(T9="","",ROUND(T9-Q9,2)) -> 2.17
A10: Empaque tapa valvulas | B10: PD511096 | C10: Pulsar N250 | D10: Motor | E10: 50 | F10: 20 | G10: 15 | H10: 1 | I10: =IF(OR(F10="",G10="",H10=""),"",F10*G10*H10) -> 300 | J10: =IF(I10="","",I10/5000) -> 0.06 | K10: 44 | L10: =IF(K10="","",ROUND(K10/Configuración!$B$4,2)) -> 0.46 | M10: =IF(E10="","",ROUND(MAX(E10/1000,IF(I10="",0,I10/5000))*Configuración!$B$10,2)) -> 1 | N10: =IF(I10="","",ROUND(I10/28316.85*Configuración!$B$15,2)) -> 0.48 | O10: =IF(L10="","",ROUND(L10*Configuración!$B$16,2)) -> 0.01 | P10: =IF(L10="","",ROUND(L10*Configuración!$B$18,2)) -> 0 | Q10: =IF(L10="","",ROUND(L10+IF(M10="",0,M10)+IF(N10="",0,N10)+IF(O10="",0,O10)+IF(P10="",0,P10),2)) -> 1.95 | R10: Gasket Cover Head Cylinder — pieza pequeña, incluir en kits de mantenimiento mayor. | S10: 0.4 | T10: =IF(Q10="","",ROUND(Q10/(1-S10),0)) -> 3 | U10: =IF(T10="","",ROUND(T10-Q10,2)) -> 1.05
A11: Pastillas freno delantero | B11: JR131827 | C11: Pulsar N250/N160 | D11: Frenos | E11: 150 | F11: 12 | G11: 8 | H11: 4 | I11: =IF(OR(F11="",G11="",H11=""),"",F11*G11*H11) -> 384 | J11: =IF(I11="","",I11/5000) -> 0.0768 | K11: 256 | L11: =IF(K11="","",ROUND(K11/Configuración!$B$4,2)) -> 2.69 | M11: =IF(E11="","",ROUND(MAX(E11/1000,IF(I11="",0,I11/5000))*Configuración!$B$10,2)) -> 2.49 | N11: =IF(I11="","",ROUND(I11/28316.85*Configuración!$B$15,2)) -> 0.61 | O11: =IF(L11="","",ROUND(L11*Configuración!$B$16,2)) -> 0.08 | P11: =IF(L11="","",ROUND(L11*Configuración!$B$18,2)) -> 0 | Q11: =IF(L11="","",ROUND(L11+IF(M11="",0,M11)+IF(N11="",0,N11)+IF(O11="",0,O11)+IF(P11="",0,P11),2)) -> 5.87 | R11: Pad Set Brake Front. | S11: 0.4 | T11: =IF(Q11="","",ROUND(Q11/(1-S11),0)) -> 10 | U11: =IF(T11="","",ROUND(T11-Q11,2)) -> 4.13
A12: Pastillas freno trasero | B12: 36DH4174 | C12: Pulsar N250/N160 | D12: Frenos | E12: 130 | F12: 10 | G12: 7 | H12: 4 | I12: =IF(OR(F12="",G12="",H12=""),"",F12*G12*H12) -> 280 | J12: =IF(I12="","",I12/5000) -> 0.056 | K12: 237 | L12: =IF(K12="","",ROUND(K12/Configuración!$B$4,2)) -> 2.49 | M12: =IF(E12="","",ROUND(MAX(E12/1000,IF(I12="",0,I12/5000))*Configuración!$B$10,2)) -> 2.16 | N12: =IF(I12="","",ROUND(I12/28316.85*Configuración!$B$15,2)) -> 0.44 | O12: =IF(L12="","",ROUND(L12*Configuración!$B$16,2)) -> 0.07 | P12: =IF(L12="","",ROUND(L12*Configuración!$B$18,2)) -> 0 | Q12: =IF(L12="","",ROUND(L12+IF(M12="",0,M12)+IF(N12="",0,N12)+IF(O12="",0,O12)+IF(P12="",0,P12),2)) -> 5.16 | R12: Disc Pad Set Rear Caliper Endu. | S12: 0.4 | T12: =IF(Q12="","",ROUND(Q12/(1-S12),0)) -> 9 | U12: =IF(T12="","",ROUND(T12-Q12,2)) -> 3.84
A13: Cable embrague | B13: JR161206 | C13: Pulsar N250/N160 | D13: Cables | E13: 160 | F13: 120 | G13: 2 | H13: 2 | I13: =IF(OR(F13="",G13="",H13=""),"",F13*G13*H13) -> 480 | J13: =IF(I13="","",I13/5000) -> 0.096 | K13: 229 | L13: =IF(K13="","",ROUND(K13/Configuración!$B$4,2)) -> 2.41 | M13: =IF(E13="","",ROUND(MAX(E13/1000,IF(I13="",0,I13/5000))*Configuración!$B$10,2)) -> 2.66 | N13: =IF(I13="","",ROUND(I13/28316.85*Configuración!$B$15,2)) -> 0.76 | O13: =IF(L13="","",ROUND(L13*Configuración!$B$16,2)) -> 0.07 | P13: =IF(L13="","",ROUND(L13*Configuración!$B$18,2)) -> 0 | Q13: =IF(L13="","",ROUND(L13+IF(M13="",0,M13)+IF(N13="",0,N13)+IF(O13="",0,O13)+IF(P13="",0,P13),2)) -> 5.9 | R13: Cable Clutch. | S13: 0.4 | T13: =IF(Q13="","",ROUND(Q13/(1-S13),0)) -> 10 | U13: =IF(T13="","",ROUND(T13-Q13,2)) -> 4.1
A14: Kit cadena | B14: JR161207 | C14: N160 | D14: Transmisión | E14: 2400 | F14: 21 | G14: 17 | H14: 7 | I14: =IF(OR(F14="",G14="",H14=""),"",F14*G14*H14) -> 2499 | J14: =IF(I14="","",I14/5000) -> 0.4998 | K14: 2000 | L14: =IF(K14="","",ROUND(K14/Configuración!$B$4,2)) -> 21.05 | M14: =IF(E14="","",ROUND(MAX(E14/1000,IF(I14="",0,I14/5000))*Configuración!$B$10,2)) -> 39.89 | N14: =IF(I14="","",ROUND(I14/28316.85*Configuración!$B$15,2)) -> 3.97 | O14: =IF(L14="","",ROUND(L14*Configuración!$B$16,2)) -> 0.63 | P14: =IF(L14="","",ROUND(L14*Configuración!$B$18,2)) -> 0 | Q14: =IF(L14="","",ROUND(L14+IF(M14="",0,M14)+IF(N14="",0,N14)+IF(O14="",0,O14)+IF(P14="",0,P14),2)) -> 65.54 | R14: Kit de cadena N160 | S14: 0.25 | T14: =IF(Q14="","",ROUND(Q14/(1-S14),0)) -> 87 | U14: =IF(T14="","",ROUND(T14-Q14,2)) -> 21.46
A15: Bomba de freno maestro | B15: JR131882 | C15: N250 | D15: Frenos | E15: 600 | F15: 22 | G15: 14 | H15: 10 | I15: =IF(OR(F15="",G15="",H15=""),"",F15*G15*H15) -> 3080 | J15: =IF(I15="","",I15/5000) -> 0.616 | K15: 1229 | L15: =IF(K15="","",ROUND(K15/Configuración!$B$4,2)) -> 12.94 | M15: =IF(E15="","",ROUND(MAX(E15/1000,IF(I15="",0,I15/5000))*Configuración!$B$10,2)) -> 10.24 | N15: =IF(I15="","",ROUND(I15/28316.85*Configuración!$B$15,2)) -> 4.89 | O15: =IF(L15="","",ROUND(L15*Configuración!$B$16,2)) -> 0.39 | P15: =IF(L15="","",ROUND(L15*Configuración!$B$18,2)) -> 0 | Q15: =IF(L15="","",ROUND(L15+IF(M15="",0,M15)+IF(N15="",0,N15)+IF(O15="",0,O15)+IF(P15="",0,P15),2)) -> 28.46 | S15: 0.4 | T15: =IF(Q15="","",ROUND(Q15/(1-S15),0)) -> 47 | U15: =IF(T15="","",ROUND(T15-Q15,2)) -> 18.54
A16: Kit bujias | B16: DG111008 | C16: Neon 150 | D16: Mantenimiento | E16: 80 | F16: 12 | G16: 4 | H16: 4 | I16: =IF(OR(F16="",G16="",H16=""),"",F16*G16*H16) -> 192 | J16: =IF(I16="","",I16/5000) -> 0.0384 | K16: 232 | L16: =IF(K16="","",ROUND(K16/Configuración!$B$4,2)) -> 2.44 | M16: =IF(E16="","",ROUND(MAX(E16/1000,IF(I16="",0,I16/5000))*Configuración!$B$10,2)) -> 1.33 | N16: =IF(I16="","",ROUND(I16/28316.85*Configuración!$B$15,2)) -> 0.31 | O16: =IF(L16="","",ROUND(L16*Configuración!$B$16,2)) -> 0.07 | P16: =IF(L16="","",ROUND(L16*Configuración!$B$18,2)) -> 0 | Q16: =IF(L16="","",ROUND(L16+IF(M16="",0,M16)+IF(N16="",0,N16)+IF(O16="",0,O16)+IF(P16="",0,P16),2)) -> 4.15 | S16: 0.4 | T16: =IF(Q16="","",ROUND(Q16/(1-S16),0)) -> 7 | U16: =IF(T16="","",ROUND(T16-Q16,2)) -> 2.85
A17: Filtro de gasolina | C17: n250 | D17: Mantenimiento | E17: 100 | F17: 10 | G17: 10 | H17: 5 | I17: =IF(OR(F17="",G17="",H17=""),"",F17*G17*H17) -> 500 | J17: =IF(I17="","",I17/5000) -> 0.1 | K17: 100 | L17: =IF(K17="","",ROUND(K17/Configuración!$B$4,2)) -> 1.05 | M17: =IF(E17="","",ROUND(MAX(E17/1000,IF(I17="",0,I17/5000))*Configuración!$B$10,2)) -> 1.66 | N17: =IF(I17="","",ROUND(I17/28316.85*Configuración!$B$15,2)) -> 0.79 | O17: =IF(L17="","",ROUND(L17*Configuración!$B$16,2)) -> 0.03 | P17: =IF(L17="","",ROUND(L17*Configuración!$B$18,2)) -> 0 | Q17: =IF(L17="","",ROUND(L17+IF(M17="",0,M17)+IF(N17="",0,N17)+IF(O17="",0,O17)+IF(P17="",0,P17),2)) -> 3.53 | S17: 0.4 | T17: =IF(Q17="","",ROUND(Q17/(1-S17),0)) -> 6 | U17: =IF(T17="","",ROUND(T17-Q17,2)) -> 2.47
A18: Tapa belly RH | B18: 52JR0131 | C18: N250 | D18: Tapas | E18: 200 | F18: 22 | G18: 14 | H18: 4 | I18: =IF(OR(F18="",G18="",H18=""),"",F18*G18*H18) -> 1232 | J18: =IF(I18="","",I18/5000) -> 0.2464 | K18: 275 | L18: =IF(K18="","",ROUND(K18/Configuración!$B$4,2)) -> 2.89 | M18: =IF(E18="","",ROUND(MAX(E18/1000,IF(I18="",0,I18/5000))*Configuración!$B$10,2)) -> 4.1 | N18: =IF(I18="","",ROUND(I18/28316.85*Configuración!$B$15,2)) -> 1.96 | O18: =IF(L18="","",ROUND(L18*Configuración!$B$16,2)) -> 0.09 | P18: =IF(L18="","",ROUND(L18*Configuración!$B$18,2)) -> 0 | Q18: =IF(L18="","",ROUND(L18+IF(M18="",0,M18)+IF(N18="",0,N18)+IF(O18="",0,O18)+IF(P18="",0,P18),2)) -> 9.04 | S18: 0.4 | T18: =IF(Q18="","",ROUND(Q18/(1-S18),0)) -> 15 | U18: =IF(T18="","",ROUND(T18-Q18,2)) -> 5.96
A19: Lockset | B19: 36JR0125 | C19: N250 | D19: Switchera | E19: 1000 | F19: 22 | G19: 16 | H19: 10 | I19: =IF(OR(F19="",G19="",H19=""),"",F19*G19*H19) -> 3520 | J19: =IF(I19="","",I19/5000) -> 0.704 | K19: 1867 | L19: =IF(K19="","",ROUND(K19/Configuración!$B$4,2)) -> 19.65 | M19: =IF(E19="","",ROUND(MAX(E19/1000,IF(I19="",0,I19/5000))*Configuración!$B$10,2)) -> 16.62 | N19: =IF(I19="","",ROUND(I19/28316.85*Configuración!$B$15,2)) -> 5.59 | O19: =IF(L19="","",ROUND(L19*Configuración!$B$16,2)) -> 0.59 | P19: =IF(L19="","",ROUND(L19*Configuración!$B$18,2)) -> 0 | Q19: =IF(L19="","",ROUND(L19+IF(M19="",0,M19)+IF(N19="",0,N19)+IF(O19="",0,O19)+IF(P19="",0,P19),2)) -> 42.45 | S19: 0.4 | T19: =IF(Q19="","",ROUND(Q19/(1-S19),0)) -> 71 | U19: =IF(T19="","",ROUND(T19-Q19,2)) -> 28.55
A20: Spark plug cap | B20: DH111015 | C20: N250 | D20: Electrico | E20: 70 | F20: 8 | G20: 6 | H20: 5 | I20: =IF(OR(F20="",G20="",H20=""),"",F20*G20*H20) -> 240 | J20: =IF(I20="","",I20/5000) -> 0.048 | K20: 242 | L20: =IF(K20="","",ROUND(K20/Configuración!$B$4,2)) -> 2.55 | M20: =IF(E20="","",ROUND(MAX(E20/1000,IF(I20="",0,I20/5000))*Configuración!$B$10,2)) -> 1.16 | N20: =IF(I20="","",ROUND(I20/28316.85*Configuración!$B$15,2)) -> 0.38 | O20: =IF(L20="","",ROUND(L20*Configuración!$B$16,2)) -> 0.08 | P20: =IF(L20="","",ROUND(L20*Configuración!$B$18,2)) -> 0 | Q20: =IF(L20="","",ROUND(L20+IF(M20="",0,M20)+IF(N20="",0,N20)+IF(O20="",0,O20)+IF(P20="",0,P20),2)) -> 4.17 | S20: 0.4 | T20: =IF(Q20="","",ROUND(Q20/(1-S20),0)) -> 7 | U20: =IF(T20="","",ROUND(T20-Q20,2)) -> 2.83
A21: Sensores 3 en 1 | B21: 36DP0112 | C21: N250 | D21: Sensores | E21: 70 | F21: 8 | G21: 6 | H21: 5 | I21: =IF(OR(F21="",G21="",H21=""),"",F21*G21*H21) -> 240 | J21: =IF(I21="","",I21/5000) -> 0.048 | K21: 1155 | L21: =IF(K21="","",ROUND(K21/Configuración!$B$4,2)) -> 12.16 | M21: =IF(E21="","",ROUND(MAX(E21/1000,IF(I21="",0,I21/5000))*Configuración!$B$10,2)) -> 1.16 | N21: =IF(I21="","",ROUND(I21/28316.85*Configuración!$B$15,2)) -> 0.38 | O21: =IF(L21="","",ROUND(L21*Configuración!$B$16,2)) -> 0.36 | P21: =IF(L21="","",ROUND(L21*Configuración!$B$18,2)) -> 0 | Q21: =IF(L21="","",ROUND(L21+IF(M21="",0,M21)+IF(N21="",0,N21)+IF(O21="",0,O21)+IF(P21="",0,P21),2)) -> 14.06 | R21: TPS, MAP sensor o MAT, IAT | S21: 0.4 | T21: =IF(Q21="","",ROUND(Q21/(1-S21),0)) -> 23 | U21: =IF(T21="","",ROUND(T21-Q21,2)) -> 8.94
A22: Tacometro | B22: JR402412 | C22: N250 | D22: Tacometro | E22: 60 | F22: 16 | G22: 12 | H22: 5 | I22: =IF(OR(F22="",G22="",H22=""),"",F22*G22*H22) -> 960 | J22: =IF(I22="","",I22/5000) -> 0.192 | K22: 70 | L22: =IF(K22="","",ROUND(K22/Configuración!$B$4,2)) -> 0.74 | M22: =IF(E22="","",ROUND(MAX(E22/1000,IF(I22="",0,I22/5000))*Configuración!$B$10,2)) -> 3.19 | N22: =IF(I22="","",ROUND(I22/28316.85*Configuración!$B$15,2)) -> 1.53 | O22: =IF(L22="","",ROUND(L22*Configuración!$B$16,2)) -> 0.02 | P22: =IF(L22="","",ROUND(L22*Configuración!$B$18,2)) -> 0 | Q22: =IF(L22="","",ROUND(L22+IF(M22="",0,M22)+IF(N22="",0,N22)+IF(O22="",0,O22)+IF(P22="",0,P22),2)) -> 5.48 | S22: 0.3 | T22: =IF(Q22="","",ROUND(Q22/(1-S22),0)) -> 8 | U22: =IF(T22="","",ROUND(T22-Q22,2)) -> 2.52
I23: =IF(OR(F23="",G23="",H23=""),"",F23*G23*H23) | J23: =IF(I23="","",I23/5000) | L23: =IF(K23="","",ROUND(K23/Configuración!$B$4,2)) | M23: =IF(E23="","",ROUND(MAX(E23/1000,IF(I23="",0,I23/5000))*Configuración!$B$10,2)) | N23: =IF(I23="","",ROUND(I23/28316.85*Configuración!$B$15,2)) | O23: =IF(L23="","",ROUND(L23*Configuración!$B$16,2)) | P23: =IF(L23="","",ROUND(L23*Configuración!$B$18,2)) | Q23: =IF(L23="","",ROUND(L23+IF(M23="",0,M23)+IF(N23="",0,N23)+IF(O23="",0,O23)+IF(P23="",0,P23),2)) | S23: 0.4 | T23: =IF(Q23="","",ROUND(Q23/(1-S23),0)) | U23: =IF(T23="","",ROUND(T23-Q23,2))
I24: =IF(OR(F24="",G24="",H24=""),"",F24*G24*H24) | J24: =IF(I24="","",I24/5000) | L24: =IF(K24="","",ROUND(K24/Configuración!$B$4,2)) | M24: =IF(E24="","",ROUND(MAX(E24/1000,IF(I24="",0,I24/5000))*Configuración!$B$10,2)) | N24: =IF(I24="","",ROUND(I24/28316.85*Configuración!$B$15,2)) | O24: =IF(L24="","",ROUND(L24*Configuración!$B$16,2)) | P24: =IF(L24="","",ROUND(L24*Configuración!$B$18,2)) | Q24: =IF(L24="","",ROUND(L24+IF(M24="",0,M24)+IF(N24="",0,N24)+IF(O24="",0,O24)+IF(P24="",0,P24),2)) | S24: 0.4 | T24: =IF(Q24="","",ROUND(Q24/(1-S24),0)) | U24: =IF(T24="","",ROUND(T24-Q24,2))
I25: =IF(OR(F25="",G25="",H25=""),"",F25*G25*H25) | J25: =IF(I25="","",I25/5000) | L25: =IF(K25="","",ROUND(K25/Configuración!$B$4,2)) | M25: =IF(E25="","",ROUND(MAX(E25/1000,IF(I25="",0,I25/5000))*Configuración!$B$10,2)) | N25: =IF(I25="","",ROUND(I25/28316.85*Configuración!$B$15,2)) | O25: =IF(L25="","",ROUND(L25*Configuración!$B$16,2)) | P25: =IF(L25="","",ROUND(L25*Configuración!$B$18,2)) | Q25: =IF(L25="","",ROUND(L25+IF(M25="",0,M25)+IF(N25="",0,N25)+IF(O25="",0,O25)+IF(P25="",0,P25),2)) | S25: 0.4 | T25: =IF(Q25="","",ROUND(Q25/(1-S25),0)) | U25: =IF(T25="","",ROUND(T25-Q25,2))
I26: =IF(OR(F26="",G26="",H26=""),"",F26*G26*H26) | J26: =IF(I26="","",I26/5000) | L26: =IF(K26="","",ROUND(K26/Configuración!$B$4,2)) | M26: =IF(E26="","",ROUND(MAX(E26/1000,IF(I26="",0,I26/5000))*Configuración!$B$10,2)) | N26: =IF(I26="","",ROUND(I26/28316.85*Configuración!$B$15,2)) | O26: =IF(L26="","",ROUND(L26*Configuración!$B$16,2)) | P26: =IF(L26="","",ROUND(L26*Configuración!$B$18,2)) | Q26: =IF(L26="","",ROUND(L26+IF(M26="",0,M26)+IF(N26="",0,N26)+IF(O26="",0,O26)+IF(P26="",0,P26),2)) | S26: 0.4 | T26: =IF(Q26="","",ROUND(Q26/(1-S26),0)) | U26: =IF(T26="","",ROUND(T26-Q26,2))
I27: =IF(OR(F27="",G27="",H27=""),"",F27*G27*H27) | J27: =IF(I27="","",I27/5000) | L27: =IF(K27="","",ROUND(K27/Configuración!$B$4,2)) | M27: =IF(E27="","",ROUND(MAX(E27/1000,IF(I27="",0,I27/5000))*Configuración!$B$10,2)) | N27: =IF(I27="","",ROUND(I27/28316.85*Configuración!$B$15,2)) | O27: =IF(L27="","",ROUND(L27*Configuración!$B$16,2)) | P27: =IF(L27="","",ROUND(L27*Configuración!$B$18,2)) | Q27: =IF(L27="","",ROUND(L27+IF(M27="",0,M27)+IF(N27="",0,N27)+IF(O27="",0,O27)+IF(P27="",0,P27),2)) | S27: 0.4 | T27: =IF(Q27="","",ROUND(Q27/(1-S27),0)) | U27: =IF(T27="","",ROUND(T27-Q27,2))
I28: =IF(OR(F28="",G28="",H28=""),"",F28*G28*H28) | J28: =IF(I28="","",I28/5000) | L28: =IF(K28="","",ROUND(K28/Configuración!$B$4,2)) | M28: =IF(E28="","",ROUND(MAX(E28/1000,IF(I28="",0,I28/5000))*Configuración!$B$10,2)) | N28: =IF(I28="","",ROUND(I28/28316.85*Configuración!$B$15,2)) | O28: =IF(L28="","",ROUND(L28*Configuración!$B$16,2)) | P28: =IF(L28="","",ROUND(L28*Configuración!$B$18,2)) | Q28: =IF(L28="","",ROUND(L28+IF(M28="",0,M28)+IF(N28="",0,N28)+IF(O28="",0,O28)+IF(P28="",0,P28),2)) | S28: 0.4 | T28: =IF(Q28="","",ROUND(Q28/(1-S28),0)) | U28: =IF(T28="","",ROUND(T28-Q28,2))
I29: =IF(OR(F29="",G29="",H29=""),"",F29*G29*H29) | J29: =IF(I29="","",I29/5000) | L29: =IF(K29="","",ROUND(K29/Configuración!$B$4,2)) | M29: =IF(E29="","",ROUND(MAX(E29/1000,IF(I29="",0,I29/5000))*Configuración!$B$10,2)) | N29: =IF(I29="","",ROUND(I29/28316.85*Configuración!$B$15,2)) | O29: =IF(L29="","",ROUND(L29*Configuración!$B$16,2)) | P29: =IF(L29="","",ROUND(L29*Configuración!$B$18,2)) | Q29: =IF(L29="","",ROUND(L29+IF(M29="",0,M29)+IF(N29="",0,N29)+IF(O29="",0,O29)+IF(P29="",0,P29),2)) | S29: 0.4 | T29: =IF(Q29="","",ROUND(Q29/(1-S29),0)) | U29: =IF(T29="","",ROUND(T29-Q29,2))
I30: =IF(OR(F30="",G30="",H30=""),"",F30*G30*H30) | J30: =IF(I30="","",I30/5000) | L30: =IF(K30="","",ROUND(K30/Configuración!$B$4,2)) | M30: =IF(E30="","",ROUND(MAX(E30/1000,IF(I30="",0,I30/5000))*Configuración!$B$10,2)) | N30: =IF(I30="","",ROUND(I30/28316.85*Configuración!$B$15,2)) | O30: =IF(L30="","",ROUND(L30*Configuración!$B$16,2)) | P30: =IF(L30="","",ROUND(L30*Configuración!$B$18,2)) | Q30: =IF(L30="","",ROUND(L30+IF(M30="",0,M30)+IF(N30="",0,N30)+IF(O30="",0,O30)+IF(P30="",0,P30),2)) | S30: 0.4 | T30: =IF(Q30="","",ROUND(Q30/(1-S30),0)) | U30: =IF(T30="","",ROUND(T30-Q30,2))
I31: =IF(OR(F31="",G31="",H31=""),"",F31*G31*H31) | J31: =IF(I31="","",I31/5000) | L31: =IF(K31="","",ROUND(K31/Configuración!$B$4,2)) | M31: =IF(E31="","",ROUND(MAX(E31/1000,IF(I31="",0,I31/5000))*Configuración!$B$10,2)) | N31: =IF(I31="","",ROUND(I31/28316.85*Configuración!$B$15,2)) | O31: =IF(L31="","",ROUND(L31*Configuración!$B$16,2)) | P31: =IF(L31="","",ROUND(L31*Configuración!$B$18,2)) | Q31: =IF(L31="","",ROUND(L31+IF(M31="",0,M31)+IF(N31="",0,N31)+IF(O31="",0,O31)+IF(P31="",0,P31),2)) | S31: 0.4 | T31: =IF(Q31="","",ROUND(Q31/(1-S31),0)) | U31: =IF(T31="","",ROUND(T31-Q31,2))
I32: =IF(OR(F32="",G32="",H32=""),"",F32*G32*H32) | J32: =IF(I32="","",I32/5000) | L32: =IF(K32="","",ROUND(K32/Configuración!$B$4,2)) | M32: =IF(E32="","",ROUND(MAX(E32/1000,IF(I32="",0,I32/5000))*Configuración!$B$10,2)) | N32: =IF(I32="","",ROUND(I32/28316.85*Configuración!$B$15,2)) | O32: =IF(L32="","",ROUND(L32*Configuración!$B$16,2)) | P32: =IF(L32="","",ROUND(L32*Configuración!$B$18,2)) | Q32: =IF(L32="","",ROUND(L32+IF(M32="",0,M32)+IF(N32="",0,N32)+IF(O32="",0,O32)+IF(P32="",0,P32),2)) | S32: 0.4 | T32: =IF(Q32="","",ROUND(Q32/(1-S32),0)) | U32: =IF(T32="","",ROUND(T32-Q32,2))
I33: =IF(OR(F33="",G33="",H33=""),"",F33*G33*H33) | J33: =IF(I33="","",I33/5000) | L33: =IF(K33="","",ROUND(K33/Configuración!$B$4,2)) | M33: =IF(E33="","",ROUND(MAX(E33/1000,IF(I33="",0,I33/5000))*Configuración!$B$10,2)) | N33: =IF(I33="","",ROUND(I33/28316.85*Configuración!$B$15,2)) | O33: =IF(L33="","",ROUND(L33*Configuración!$B$16,2)) | P33: =IF(L33="","",ROUND(L33*Configuración!$B$18,2)) | Q33: =IF(L33="","",ROUND(L33+IF(M33="",0,M33)+IF(N33="",0,N33)+IF(O33="",0,O33)+IF(P33="",0,P33),2)) | S33: 0.4 | T33: =IF(Q33="","",ROUND(Q33/(1-S33),0)) | U33: =IF(T33="","",ROUND(T33-Q33,2))
I34: =IF(OR(F34="",G34="",H34=""),"",F34*G34*H34) | J34: =IF(I34="","",I34/5000) | L34: =IF(K34="","",ROUND(K34/Configuración!$B$4,2)) | M34: =IF(E34="","",ROUND(MAX(E34/1000,IF(I34="",0,I34/5000))*Configuración!$B$10,2)) | N34: =IF(I34="","",ROUND(I34/28316.85*Configuración!$B$15,2)) | O34: =IF(L34="","",ROUND(L34*Configuración!$B$16,2)) | P34: =IF(L34="","",ROUND(L34*Configuración!$B$18,2)) | Q34: =IF(L34="","",ROUND(L34+IF(M34="",0,M34)+IF(N34="",0,N34)+IF(O34="",0,O34)+IF(P34="",0,P34),2)) | S34: 0.4 | T34: =IF(Q34="","",ROUND(Q34/(1-S34),0)) | U34: =IF(T34="","",ROUND(T34-Q34,2))
... I39: =IF(OR(F39="",G39="",H39=""),"",F39*G39*H39) | J39: =IF(I39="","",I39/5000) | L39: =IF(K39="","",ROUND(K39/Configuración!$B$4,2)) | M39: =IF(E39="","",ROUND(MAX(E39/1000,IF(I39="",0,I39/5000))*Configuración!$B$10,2)) | N39: =IF(I39="","",ROUND(I39/28316.85*Configuración!$B$15,2)) | O39: =IF(L39="","",ROUND(L39*Configuración!$B$16,2)) | P39: =IF(L39="","",ROUND(L39*Configuración!$B$18,2)) | Q39: =IF(L39="","",ROUND(L39+IF(M39="",0,M39)+IF(N39="",0,N39)+IF(O39="",0,O39)+IF(P39="",0,P39),2)) | S39: 0.4 | T39: =IF(Q39="","",ROUND(Q39/(1-S39),0)) | U39: =IF(T39="","",ROUND(T39-Q39,2))

Sheet Próximo Pedido
A1: 🛒 PRÓXIMO PEDIDO — Armar y calcular antes de comprar
A2: Pega el nombre del producto igual que en Catálogo para que el BUSCARV traiga peso y precio automático.
A4: Producto (igual que Catálogo) | B4: Cant. | C4: Precio INR (auto) | D4: Peso g (auto) | E4: Vol cm³ (auto) | F4: Peso fact. (kg) | G4: Envío ($) | H4: Seguro Shoppre ($) | I4: Costo total ($) | J4: Margen (%) | K4: Precio venta ($) | L4: Ganancia ($) | M4: Cliente
B5: 1 | C5: =IF(A5="","",IFERROR(VLOOKUP(A5,Catálogo!$A$5:$U$39,11,0),"¿no encontrado?")) | D5: =IF(A5="","",IFERROR(VLOOKUP(A5,Catálogo!$A$5:$U$39,5,0),"")) | E5: =IF(A5="","",IFERROR(VLOOKUP(A5,Catálogo!$A$5:$U$39,9,0),"")) | F5: =IF(OR(A5="",D5=""),"",B5*MAX(D5/1000,IF(E5="",0,E5/5000))) | G5: =IF(OR(F5="",E5=""),"",ROUND(F5*Configuración!$B$10 + B5*E5/28316.85*Configuración!$B$15,2)) | H5: =IF(C5="","",ROUND(B5*(C5/Configuración!$B$4)*Configuración!$B$16,2)) | I5: =IF(C5="","",ROUND(B5*(C5/Configuración!$B$4)+IF(G5="",0,G5)+IF(H5="",0,H5),2)) | J5: =IF(A5="","",IFERROR(VLOOKUP(A5,Catálogo!$A$5:$U$39,19,0),0.4)) | K5: =IF(I5="","",ROUND(I5/(1-J5),0)) | L5: =IF(K5="","",ROUND(K5-I5,2))
B6: 1 | C6: =IF(A6="","",IFERROR(VLOOKUP(A6,Catálogo!$A$5:$U$39,11,0),"¿no encontrado?")) | D6: =IF(A6="","",IFERROR(VLOOKUP(A6,Catálogo!$A$5:$U$39,5,0),"")) | E6: =IF(A6="","",IFERROR(VLOOKUP(A6,Catálogo!$A$5:$U$39,9,0),"")) | F6: =IF(OR(A6="",D6=""),"",B6*MAX(D6/1000,IF(E6="",0,E6/5000))) | G6: =IF(OR(F6="",E6=""),"",ROUND(F6*Configuración!$B$10 + B6*E6/28316.85*Configuración!$B$15,2)) | H6: =IF(C6="","",ROUND(B6*(C6/Configuración!$B$4)*Configuración!$B$16,2)) | I6: =IF(C6="","",ROUND(B6*(C6/Configuración!$B$4)+IF(G6="",0,G6)+IF(H6="",0,H6),2)) | J6: =IF(A6="","",IFERROR(VLOOKUP(A6,Catálogo!$A$5:$U$39,19,0),0.4)) | K6: =IF(I6="","",ROUND(I6/(1-J6),0)) | L6: =IF(K6="","",ROUND(K6-I6,2))
B7: 1 | C7: =IF(A7="","",IFERROR(VLOOKUP(A7,Catálogo!$A$5:$U$39,11,0),"¿no encontrado?")) | D7: =IF(A7="","",IFERROR(VLOOKUP(A7,Catálogo!$A$5:$U$39,5,0),"")) | E7: =IF(A7="","",IFERROR(VLOOKUP(A7,Catálogo!$A$5:$U$39,9,0),"")) | F7: =IF(OR(A7="",D7=""),"",B7*MAX(D7/1000,IF(E7="",0,E7/5000))) | G7: =IF(OR(F7="",E7=""),"",ROUND(F7*Configuración!$B$10 + B7*E7/28316.85*Configuración!$B$15,2)) | H7: =IF(C7="","",ROUND(B7*(C7/Configuración!$B$4)*Configuración!$B$16,2)) | I7: =IF(C7="","",ROUND(B7*(C7/Configuración!$B$4)+IF(G7="",0,G7)+IF(H7="",0,H7),2)) | J7: =IF(A7="","",IFERROR(VLOOKUP(A7,Catálogo!$A$5:$U$39,19,0),0.4)) | K7: =IF(I7="","",ROUND(I7/(1-J7),0)) | L7: =IF(K7="","",ROUND(K7-I7,2))
B8: 1 | C8: =IF(A8="","",IFERROR(VLOOKUP(A8,Catálogo!$A$5:$U$39,11,0),"¿no encontrado?")) | D8: =IF(A8="","",IFERROR(VLOOKUP(A8,Catálogo!$A$5:$U$39,5,0),"")) | E8: =IF(A8="","",IFERROR(VLOOKUP(A8,Catálogo!$A$5:$U$39,9,0),"")) | F8: =IF(OR(A8="",D8=""),"",B8*MAX(D8/1000,IF(E8="",0,E8/5000))) | G8: =IF(OR(F8="",E8=""),"",ROUND(F8*Configuración!$B$10 + B8*E8/28316.85*Configuración!$B$15,2)) | H8: =IF(C8="","",ROUND(B8*(C8/Configuración!$B$4)*Configuración!$B$16,2)) | I8: =IF(C8="","",ROUND(B8*(C8/Configuración!$B$4)+IF(G8="",0,G8)+IF(H8="",0,H8),2)) | J8: =IF(A8="","",IFERROR(VLOOKUP(A8,Catálogo!$A$5:$U$39,19,0),0.4)) | K8: =IF(I8="","",ROUND(I8/(1-J8),0)) | L8: =IF(K8="","",ROUND(K8-I8,2))
B9: 1 | C9: =IF(A9="","",IFERROR(VLOOKUP(A9,Catálogo!$A$5:$U$39,11,0),"¿no encontrado?")) | D9: =IF(A9="","",IFERROR(VLOOKUP(A9,Catálogo!$A$5:$U$39,5,0),"")) | E9: =IF(A9="","",IFERROR(VLOOKUP(A9,Catálogo!$A$5:$U$39,9,0),"")) | F9: =IF(OR(A9="",D9=""),"",B9*MAX(D9/1000,IF(E9="",0,E9/5000))) | G9: =IF(OR(F9="",E9=""),"",ROUND(F9*Configuración!$B$10 + B9*E9/28316.85*Configuración!$B$15,2)) | H9: =IF(C9="","",ROUND(B9*(C9/Configuración!$B$4)*Configuración!$B$16,2)) | I9: =IF(C9="","",ROUND(B9*(C9/Configuración!$B$4)+IF(G9="",0,G9)+IF(H9="",0,H9),2)) | J9: =IF(A9="","",IFERROR(VLOOKUP(A9,Catálogo!$A$5:$U$39,19,0),0.4)) | K9: =IF(I9="","",ROUND(I9/(1-J9),0)) | L9: =IF(K9="","",ROUND(K9-I9,2))
B10: 1 | C10: =IF(A10="","",IFERROR(VLOOKUP(A10,Catálogo!$A$5:$U$39,11,0),"¿no encontrado?")) | D10: =IF(A10="","",IFERROR(VLOOKUP(A10,Catálogo!$A$5:$U$39,5,0),"")) | E10: =IF(A10="","",IFERROR(VLOOKUP(A10,Catálogo!$A$5:$U$39,9,0),"")) | F10: =IF(OR(A10="",D10=""),"",B10*MAX(D10/1000,IF(E10="",0,E10/5000))) | G10: =IF(OR(F10="",E10=""),"",ROUND(F10*Configuración!$B$10 + B10*E10/28316.85*Configuración!$B$15,2)) | H10: =IF(C10="","",ROUND(B10*(C10/Configuración!$B$4)*Configuración!$B$16,2)) | I10: =IF(C10="","",ROUND(B10*(C10/Configuración!$B$4)+IF(G10="",0,G10)+IF(H10="",0,H10),2)) | J10: =IF(A10="","",IFERROR(VLOOKUP(A10,Catálogo!$A$5:$U$39,19,0),0.4)) | K10: =IF(I10="","",ROUND(I10/(1-J10),0)) | L10: =IF(K10="","",ROUND(K10-I10,2))
B11: 1 | C11: =IF(A11="","",IFERROR(VLOOKUP(A11,Catálogo!$A$5:$U$39,11,0),"¿no encontrado?")) | D11: =IF(A11="","",IFERROR(VLOOKUP(A11,Catálogo!$A$5:$U$39,5,0),"")) | E11: =IF(A11="","",IFERROR(VLOOKUP(A11,Catálogo!$A$5:$U$39,9,0),"")) | F11: =IF(OR(A11="",D11=""),"",B11*MAX(D11/1000,IF(E11="",0,E11/5000))) | G11: =IF(OR(F11="",E11=""),"",ROUND(F11*Configuración!$B$10 + B11*E11/28316.85*Configuración!$B$15,2)) | H11: =IF(C11="","",ROUND(B11*(C11/Configuración!$B$4)*Configuración!$B$16,2)) | I11: =IF(C11="","",ROUND(B11*(C11/Configuración!$B$4)+IF(G11="",0,G11)+IF(H11="",0,H11),2)) | J11: =IF(A11="","",IFERROR(VLOOKUP(A11,Catálogo!$A$5:$U$39,19,0),0.4)) | K11: =IF(I11="","",ROUND(I11/(1-J11),0)) | L11: =IF(K11="","",ROUND(K11-I11,2))
B12: 1 | C12: =IF(A12="","",IFERROR(VLOOKUP(A12,Catálogo!$A$5:$U$39,11,0),"¿no encontrado?")) | D12: =IF(A12="","",IFERROR(VLOOKUP(A12,Catálogo!$A$5:$U$39,5,0),"")) | E12: =IF(A12="","",IFERROR(VLOOKUP(A12,Catálogo!$A$5:$U$39,9,0),"")) | F12: =IF(OR(A12="",D12=""),"",B12*MAX(D12/1000,IF(E12="",0,E12/5000))) | G12: =IF(OR(F12="",E12=""),"",ROUND(F12*Configuración!$B$10 + B12*E12/28316.85*Configuración!$B$15,2)) | H12: =IF(C12="","",ROUND(B12*(C12/Configuración!$B$4)*Configuración!$B$16,2)) | I12: =IF(C12="","",ROUND(B12*(C12/Configuración!$B$4)+IF(G12="",0,G12)+IF(H12="",0,H12),2)) | J12: =IF(A12="","",IFERROR(VLOOKUP(A12,Catálogo!$A$5:$U$39,19,0),0.4)) | K12: =IF(I12="","",ROUND(I12/(1-J12),0)) | L12: =IF(K12="","",ROUND(K12-I12,2))
B13: 1 | C13: =IF(A13="","",IFERROR(VLOOKUP(A13,Catálogo!$A$5:$U$39,11,0),"¿no encontrado?")) | D13: =IF(A13="","",IFERROR(VLOOKUP(A13,Catálogo!$A$5:$U$39,5,0),"")) | E13: =IF(A13="","",IFERROR(VLOOKUP(A13,Catálogo!$A$5:$U$39,9,0),"")) | F13: =IF(OR(A13="",D13=""),"",B13*MAX(D13/1000,IF(E13="",0,E13/5000))) | G13: =IF(OR(F13="",E13=""),"",ROUND(F13*Configuración!$B$10 + B13*E13/28316.85*Configuración!$B$15,2)) | H13: =IF(C13="","",ROUND(B13*(C13/Configuración!$B$4)*Configuración!$B$16,2)) | I13: =IF(C13="","",ROUND(B13*(C13/Configuración!$B$4)+IF(G13="",0,G13)+IF(H13="",0,H13),2)) | J13: =IF(A13="","",IFERROR(VLOOKUP(A13,Catálogo!$A$5:$U$39,19,0),0.4)) | K13: =IF(I13="","",ROUND(I13/(1-J13),0)) | L13: =IF(K13="","",ROUND(K13-I13,2))
B14: 1 | C14: =IF(A14="","",IFERROR(VLOOKUP(A14,Catálogo!$A$5:$U$39,11,0),"¿no encontrado?")) | D14: =IF(A14="","",IFERROR(VLOOKUP(A14,Catálogo!$A$5:$U$39,5,0),"")) | E14: =IF(A14="","",IFERROR(VLOOKUP(A14,Catálogo!$A$5:$U$39,9,0),"")) | F14: =IF(OR(A14="",D14=""),"",B14*MAX(D14/1000,IF(E14="",0,E14/5000))) | G14: =IF(OR(F14="",E14=""),"",ROUND(F14*Configuración!$B$10 + B14*E14/28316.85*Configuración!$B$15,2)) | H14: =IF(C14="","",ROUND(B14*(C14/Configuración!$B$4)*Configuración!$B$16,2)) | I14: =IF(C14="","",ROUND(B14*(C14/Configuración!$B$4)+IF(G14="",0,G14)+IF(H14="",0,H14),2)) | J14: =IF(A14="","",IFERROR(VLOOKUP(A14,Catálogo!$A$5:$U$39,19,0),0.4)) | K14: =IF(I14="","",ROUND(I14/(1-J14),0)) | L14: =IF(K14="","",ROUND(K14-I14,2))
B15: 1 | C15: =IF(A15="","",IFERROR(VLOOKUP(A15,Catálogo!$A$5:$U$39,11,0),"¿no encontrado?")) | D15: =IF(A15="","",IFERROR(VLOOKUP(A15,Catálogo!$A$5:$U$39,5,0),"")) | E15: =IF(A15="","",IFERROR(VLOOKUP(A15,Catálogo!$A$5:$U$39,9,0),"")) | F15: =IF(OR(A15="",D15=""),"",B15*MAX(D15/1000,IF(E15="",0,E15/5000))) | G15: =IF(OR(F15="",E15=""),"",ROUND(F15*Configuración!$B$10 + B15*E15/28316.85*Configuración!$B$15,2)) | H15: =IF(C15="","",ROUND(B15*(C15/Configuración!$B$4)*Configuración!$B$16,2)) | I15: =IF(C15="","",ROUND(B15*(C15/Configuración!$B$4)+IF(G15="",0,G15)+IF(H15="",0,H15),2)) | J15: =IF(A15="","",IFERROR(VLOOKUP(A15,Catálogo!$A$5:$U$39,19,0),0.4)) | K15: =IF(I15="","",ROUND(I15/(1-J15),0)) | L15: =IF(K15="","",ROUND(K15-I15,2))
B16: 1 | C16: =IF(A16="","",IFERROR(VLOOKUP(A16,Catálogo!$A$5:$U$39,11,0),"¿no encontrado?")) | D16: =IF(A16="","",IFERROR(VLOOKUP(A16,Catálogo!$A$5:$U$39,5,0),"")) | E16: =IF(A16="","",IFERROR(VLOOKUP(A16,Catálogo!$A$5:$U$39,9,0),"")) | F16: =IF(OR(A16="",D16=""),"",B16*MAX(D16/1000,IF(E16="",0,E16/5000))) | G16: =IF(OR(F16="",E16=""),"",ROUND(F16*Configuración!$B$10 + B16*E16/28316.85*Configuración!$B$15,2)) | H16: =IF(C16="","",ROUND(B16*(C16/Configuración!$B$4)*Configuración!$B$16,2)) | I16: =IF(C16="","",ROUND(B16*(C16/Configuración!$B$4)+IF(G16="",0,G16)+IF(H16="",0,H16),2)) | J16: =IF(A16="","",IFERROR(VLOOKUP(A16,Catálogo!$A$5:$U$39,19,0),0.4)) | K16: =IF(I16="","",ROUND(I16/(1-J16),0)) | L16: =IF(K16="","",ROUND(K16-I16,2))
... B24: 1 | C24: =IF(A24="","",IFERROR(VLOOKUP(A24,Catálogo!$A$5:$U$39,11,0),"¿no encontrado?")) | D24: =IF(A24="","",IFERROR(VLOOKUP(A24,Catálogo!$A$5:$U$39,5,0),"")) | E24: =IF(A24="","",IFERROR(VLOOKUP(A24,Catálogo!$A$5:$U$39,9,0),"")) | F24: =IF(OR(A24="",D24=""),"",B24*MAX(D24/1000,IF(E24="",0,E24/5000))) | G24: =IF(OR(F24="",E24=""),"",ROUND(F24*Configuración!$B$10 + B24*E24/28316.85*Configuración!$B$15,2)) | H24: =IF(C24="","",ROUND(B24*(C24/Configuración!$B$4)*Configuración!$B$16,2)) | I24: =IF(C24="","",ROUND(B24*(C24/Configuración!$B$4)+IF(G24="",0,G24)+IF(H24="",0,H24),2)) | J24: =IF(A24="","",IFERROR(VLOOKUP(A24,Catálogo!$A$5:$U$39,19,0),0.4)) | K24: =IF(I24="","",ROUND(I24/(1-J24),0)) | L24: =IF(K24="","",ROUND(K24-I24,2))
A25: TOTALES | F25: =IF(COUNTA(F5:F24)=0,"",SUM(F5:F24)) -> 0 | G25: =IF(COUNTA(G5:G24)=0,"",SUM(G5:G24)) -> 0 | H25: =IF(COUNTA(H5:H24)=0,"",SUM(H5:H24)) -> 0 | I25: =IF(COUNTA(I5:I24)=0,"",SUM(I5:I24)) -> 0 | K25: =IF(COUNTA(K5:K24)=0,"",SUM(K5:K24)) -> 0 | L25: =IF(COUNTA(L5:L24)=0,"",SUM(L5:L24)) -> 0
A27: RESUMEN DEL ENVÍO
A28: Peso facturable total (kg) | B28: =IF(I25="","",ROUND(SUM(F5:F24),2)) -> 0
A29: Valor total mercancía (USD) | B29: =IF(I25="","",ROUND(I25-IF(G25="",0,G25)-IF(H25="",0,H25),2)) -> 0
A30: Ganancia total estimada | B30: =IF(L25="","",L25) -> 0
A31: Margen promedio | B31: =IFERROR(AVERAGE(J5:J24),"—") -> —
A32: Valor declarado total (USD) | B32: =IF(B29="","",B29) -> 0 | C32: Base para calcular seguro — valor FOB total de la mercancía
A33: Seguro Shoppre (3% declarado) | B33: =IF(B32="","",ROUND(B32*Configuración!$B$16,2)) -> 0 | C33: 3% × valor declarado
A34: Processing fee Shoppre (fijo) | B34: =IF(B29="","",ROUND(Configuración!$B$17/Configuración!$B$4,2)) -> 5.26 | C34: ₹500 ÷ tasa INR — cargo fijo por envío
A35: Total costos del envío (con seguro) | B35: =IF(B29="","",ROUND(SUM(B33:B34),2)) -> 5.26 | C35: Seguro + processing fee — sumar al costo total del pedido
A36: Envío real Duty Free (tabla, peso total) | B36: =IF(B28="","",IFERROR(IF(Configuración!$B$8,INDEX('Tarifas Shoppre'!$E$4:$E$219,MATCH(MIN(22,MAX(0.5,ROUND(CEILING(B28,0.1),1))),'Tarifas Shoppre'!$A$4:$A$219,1)),INDEX('Tarifas Shoppre'!$D$4:$D$219,MATCH(MIN(22,MAX(0.5,ROUND(CEILING(B28,0.1),1))),'Tarifas Shoppre'!$A$4:$A$219,1))),0)) -> 20.72 | C36: Costo Duty Free real del peso total. Úsalo para verificar la suma por ítem.

Sheet Calculadora
A1: 🏍 CALCULADORA DE PRECIOS — India → Miami → Caracas
A2: Ruta: 99rpm / Boodmo → Shoppre + FedEx → Miami → Liberty Express → Caracas
A4: Producto | B4: Precio India (INR ₹) | C4: Precio India (USD $) | D4: Peso real (gramos) | E4: Vol. L×A×H (cm³) | F4: Peso fact. (kg) | G4: Valor declarado ($) | H4: Envío total ($) | I4: SENIAT ($) | J4: Costo total ($) | K4: Margen (%) | L4: Precio venta ($) | M4: Precio venta (Bs.D) | N4: Ganancia ($)
C5: =IF(B5="","",B5/Configuración!$B$4) | F5: =IF(D5="","",MAX(D5/1000,IF(E5="",0,E5/5000))) | H5: =IF(F5="","",ROUND(F5*Configuración!$B$10 + IF(E5="",0,E5/28316.85)*Configuración!$B$15,2)) | I5: =IF(G5="","",IF(G5>Configuración!$B$21,G5*Configuración!$B$22,0)) | J5: =IF(C5="","",C5+IF(H5="",0,H5)+IF(I5="",0,I5)) | K5: 0.4 | L5: =IF(J5="","",J5/(1-K5)) | M5: =IF(L5="","",L5*Configuración!$B$5) | N5: =IF(L5="","",L5-J5)
C6: =IF(B6="","",B6/Configuración!$B$4) | F6: =IF(D6="","",MAX(D6/1000,IF(E6="",0,E6/5000))) | H6: =IF(F6="","",ROUND(F6*Configuración!$B$10 + IF(E6="",0,E6/28316.85)*Configuración!$B$15,2)) | I6: =IF(G6="","",IF(G6>Configuración!$B$21,G6*Configuración!$B$22,0)) | J6: =IF(C6="","",C6+IF(H6="",0,H6)+IF(I6="",0,I6)) | K6: 0.4 | L6: =IF(J6="","",J6/(1-K6)) | M6: =IF(L6="","",L6*Configuración!$B$5) | N6: =IF(L6="","",L6-J6)
C7: =IF(B7="","",B7/Configuración!$B$4) | F7: =IF(D7="","",MAX(D7/1000,IF(E7="",0,E7/5000))) | H7: =IF(F7="","",ROUND(F7*Configuración!$B$10 + IF(E7="",0,E7/28316.85)*Configuración!$B$15,2)) | I7: =IF(G7="","",IF(G7>Configuración!$B$21,G7*Configuración!$B$22,0)) | J7: =IF(C7="","",C7+IF(H7="",0,H7)+IF(I7="",0,I7)) | K7: 0.4 | L7: =IF(J7="","",J7/(1-K7)) | M7: =IF(L7="","",L7*Configuración!$B$5) | N7: =IF(L7="","",L7-J7)
C8: =IF(B8="","",B8/Configuración!$B$4) | F8: =IF(D8="","",MAX(D8/1000,IF(E8="",0,E8/5000))) | H8: =IF(F8="","",ROUND(F8*Configuración!$B$10 + IF(E8="",0,E8/28316.85)*Configuración!$B$15,2)) | I8: =IF(G8="","",IF(G8>Configuración!$B$21,G8*Configuración!$B$22,0)) | J8: =IF(C8="","",C8+IF(H8="",0,H8)+IF(I8="",0,I8)) | K8: 0.4 | L8: =IF(J8="","",J8/(1-K8)) | M8: =IF(L8="","",L8*Configuración!$B$5) | N8: =IF(L8="","",L8-J8)
C9: =IF(B9="","",B9/Configuración!$B$4) | F9: =IF(D9="","",MAX(D9/1000,IF(E9="",0,E9/5000))) | H9: =IF(F9="","",ROUND(F9*Configuración!$B$10 + IF(E9="",0,E9/28316.85)*Configuración!$B$15,2)) | I9: =IF(G9="","",IF(G9>Configuración!$B$21,G9*Configuración!$B$22,0)) | J9: =IF(C9="","",C9+IF(H9="",0,H9)+IF(I9="",0,I9)) | K9: 0.4 | L9: =IF(J9="","",J9/(1-K9)) | M9: =IF(L9="","",L9*Configuración!$B$5) | N9: =IF(L9="","",L9-J9)
C10: =IF(B10="","",B10/Configuración!$B$4) | F10: =IF(D10="","",MAX(D10/1000,IF(E10="",0,E10/5000))) | H10: =IF(F10="","",ROUND(F10*Configuración!$B$10 + IF(E10="",0,E10/28316.85)*Configuración!$B$15,2)) | I10: =IF(G10="","",IF(G10>Configuración!$B$21,G10*Configuración!$B$22,0)) | J10: =IF(C10="","",C10+IF(H10="",0,H10)+IF(I10="",0,I10)) | K10: 0.4 | L10: =IF(J10="","",J10/(1-K10)) | M10: =IF(L10="","",L10*Configuración!$B$5) | N10: =IF(L10="","",L10-J10)
C11: =IF(B11="","",B11/Configuración!$B$4) | F11: =IF(D11="","",MAX(D11/1000,IF(E11="",0,E11/5000))) | H11: =IF(F11="","",ROUND(F11*Configuración!$B$10 + IF(E11="",0,E11/28316.85)*Configuración!$B$15,2)) | I11: =IF(G11="","",IF(G11>Configuración!$B$21,G11*Configuración!$B$22,0)) | J11: =IF(C11="","",C11+IF(H11="",0,H11)+IF(I11="",0,I11)) | K11: 0.4 | L11: =IF(J11="","",J11/(1-K11)) | M11: =IF(L11="","",L11*Configuración!$B$5) | N11: =IF(L11="","",L11-J11)
C12: =IF(B12="","",B12/Configuración!$B$4) | F12: =IF(D12="","",MAX(D12/1000,IF(E12="",0,E12/5000))) | H12: =IF(F12="","",ROUND(F12*Configuración!$B$10 + IF(E12="",0,E12/28316.85)*Configuración!$B$15,2)) | I12: =IF(G12="","",IF(G12>Configuración!$B$21,G12*Configuración!$B$22,0)) | J12: =IF(C12="","",C12+IF(H12="",0,H12)+IF(I12="",0,I12)) | K12: 0.4 | L12: =IF(J12="","",J12/(1-K12)) | M12: =IF(L12="","",L12*Configuración!$B$5) | N12: =IF(L12="","",L12-J12)
C13: =IF(B13="","",B13/Configuración!$B$4) | F13: =IF(D13="","",MAX(D13/1000,IF(E13="",0,E13/5000))) | H13: =IF(F13="","",ROUND(F13*Configuración!$B$10 + IF(E13="",0,E13/28316.85)*Configuración!$B$15,2)) | I13: =IF(G13="","",IF(G13>Configuración!$B$21,G13*Configuración!$B$22,0)) | J13: =IF(C13="","",C13+IF(H13="",0,H13)+IF(I13="",0,I13)) | K13: 0.4 | L13: =IF(J13="","",J13/(1-K13)) | M13: =IF(L13="","",L13*Configuración!$B$5) | N13: =IF(L13="","",L13-J13)
C14: =IF(B14="","",B14/Configuración!$B$4) | F14: =IF(D14="","",MAX(D14/1000,IF(E14="",0,E14/5000))) | H14: =IF(F14="","",ROUND(F14*Configuración!$B$10 + IF(E14="",0,E14/28316.85)*Configuración!$B$15,2)) | I14: =IF(G14="","",IF(G14>Configuración!$B$21,G14*Configuración!$B$22,0)) | J14: =IF(C14="","",C14+IF(H14="",0,H14)+IF(I14="",0,I14)) | K14: 0.4 | L14: =IF(J14="","",J14/(1-K14)) | M14: =IF(L14="","",L14*Configuración!$B$5) | N14: =IF(L14="","",L14-J14)
C15: =IF(B15="","",B15/Configuración!$B$4) | F15: =IF(D15="","",MAX(D15/1000,IF(E15="",0,E15/5000))) | H15: =IF(F15="","",ROUND(F15*Configuración!$B$10 + IF(E15="",0,E15/28316.85)*Configuración!$B$15,2)) | I15: =IF(G15="","",IF(G15>Configuración!$B$21,G15*Configuración!$B$22,0)) | J15: =IF(C15="","",C15+IF(H15="",0,H15)+IF(I15="",0,I15)) | K15: 0.4 | L15: =IF(J15="","",J15/(1-K15)) | M15: =IF(L15="","",L15*Configuración!$B$5) | N15: =IF(L15="","",L15-J15)
C16: =IF(B16="","",B16/Configuración!$B$4) | F16: =IF(D16="","",MAX(D16/1000,IF(E16="",0,E16/5000))) | H16: =IF(F16="","",ROUND(F16*Configuración!$B$10 + IF(E16="",0,E16/28316.85)*Configuración!$B$15,2)) | I16: =IF(G16="","",IF(G16>Configuración!$B$21,G16*Configuración!$B$22,0)) | J16: =IF(C16="","",C16+IF(H16="",0,H16)+IF(I16="",0,I16)) | K16: 0.4 | L16: =IF(J16="","",J16/(1-K16)) | M16: =IF(L16="","",L16*Configuración!$B$5) | N16: =IF(L16="","",L16-J16)
... C24: =IF(B24="","",B24/Configuración!$B$4) | F24: =IF(D24="","",MAX(D24/1000,IF(E24="",0,E24/5000))) | H24: =IF(F24="","",ROUND(F24*Configuración!$B$10 + IF(E24="",0,E24/28316.85)*Configuración!$B$15,2)) | I24: =IF(G24="","",IF(G24>Configuración!$B$21,G24*Configuración!$B$22,0)) | J24: =IF(C24="","",C24+IF(H24="",0,H24)+IF(I24="",0,I24)) | K24: 0.4 | L24: =IF(J24="","",J24/(1-K24)) | M24: =IF(L24="","",L24*Configuración!$B$5) | N24: =IF(L24="","",L24-J24)
A25: TOTALES / PROMEDIO | J25: =IF(COUNTA(J5:J24)=0,"",SUM(J5:J24)) -> 0 | K25: =IF(COUNTA(K5:K24)=0,"",AVERAGE(K5:K24)) -> 0.4 | L25: =IF(COUNTA(L5:L24)=0,"",SUM(L5:L24)) -> 0 | M25: =IF(COUNTA(M5:M24)=0,"",SUM(M5:M24)) -> 0 | N25: =IF(COUNTA(N5:N24)=0,"",SUM(N5:N24)) -> 0

Sheet Simulador Envío
A1: 📦 SIMULADOR DE ENVÍO CONSOLIDADO
A3: DATOS DEL ENVÍO
A4: Número de clientes | B4: 4 | D4: Clientes en este envío
A5: Peso total (kg) | B5: 5.8 | C5: kg | D5: Suma de todos los paquetes
A6: Valor total mercancía | B6: 58 | C6: USD | D6: FOB India — para seguro
A7: Valor declarado total | B7: 85 | C7: USD | D7: Lo que se declara en aduana
A8: Volumen total del envío | B8: 0 | C8: ft³ | D8: Suma volúmenes (L×A×H cm³) ÷ 28317 por ítem — o medir cajas directamente
A9: COSTOS DEL ENVÍO
A10: Envío India → Miami (Duty Free) | B10: =IFERROR(IF(Configuración!$B$8,INDEX('Tarifas Shoppre'!$E$4:$E$219,MATCH(MIN(22,MAX(0.5,ROUND(CEILING(B5,0.1),1))),'Tarifas Shoppre'!$A$4:$A$219,1)),INDEX('Tarifas Shoppre'!$D$4:$D$219,MATCH(MIN(22,MAX(0.5,ROUND(CEILING(B5,0.1),1))),'Tarifas Shoppre'!$A$4:$A$219,1))),0) -> 109.02 | C10: USD | D10: Costo Duty Free real del peso total (tabla Tarifas Shoppre). Arancel USA ya incluido.
A11: Envío Miami → Caracas | B11: =B8*Configuración!$B$15 -> 0 | C11: USD
A12: SENIAT | B12: =IF(B7>Configuración!$B$21,B7*Configuración!$B$22,0) -> 0 | C12: USD | D12: Aduana Venezuela según umbral/tasa en Configuración.
A13: Costo logístico total | B13: =B10+B11+B12 -> 109.02 | C13: USD
A14: Costo por kg (tramo India→Miami) | B14: =IF(B5=0,"",B13/B5) -> 18.796552 | C14: USD/kg
A15: Costo por cliente (avg) | B15: =IF(B4=0,"",B13/B4) -> 27.255 | C15: USD/cliente
